AUTHORS
LICENSE
MANIFEST.in
README.md
setup.py
rbmozui/__init__.py
rbmozui/admin_urls.py
rbmozui/extension.py
rbmozui/fields.py
rbmozui.egg-info/PKG-INFO
rbmozui.egg-info/SOURCES.txt
rbmozui.egg-info/dependency_links.txt
rbmozui.egg-info/entry_points.txt
rbmozui.egg-info/not-zip-safe
rbmozui.egg-info/top_level.txt
rbmozui/templatetags/__init__.py
rbmozui/templatetags/rbmozui.py