Metadata-Version: 1.0
Name: rbmozui
Version: 0.2.13beta0
Summary: UI tweaks to Review Board for Mozilla
Home-page: UNKNOWN
Author: UNKNOWN
Author-email: UNKNOWN
License: MIT
Platform: UNKNOWN
Classifier: Intended Audience :: Developers
Classifier: License :: OSI Approved :: MIT License
